[
  {
    "date": "2026-04-19",
    "pillar": "career-advice",
    "hookStyle": "a direct question to the audience",
    "hook": "Thinking of a Career in Cybersecurity?",
    "caption": "Ready to break into cybersecurity? Let's get started! 💻☕️ #CybersecurityCareers #CareerAdvice #TechJobs #JobSearch #CypherJobs"
  },
  {
    "date": "2026-04-19",
    "pillar": "certs",
    "hookStyle": "a \"stop doing X\" warning",
    "hook": "Stop Wasting Time on the Wrong Certs!",
    "caption": "Feeling lost choosing the right cybersecurity cert? ☕️ Let's break it down together! #Cybersecurity #CareerAdvice #Certifications #StudyTips #TechCareers"
  }
]